<?xml version="1.0" encoding="UTF-8"?>
<TABLE>
    <METADATA>
        <NAME>P_45_TB</NAME>
        <COL>P_ID</COL>
        <COL>PROJECT_NAME</COL>
        <COL>LICENSE_ID</COL>
        <COL>LICENSE_NAME</COL>
        <COL>LICENSE_DISPLAY</COL>
        <COL>SIZE</COL>
        <COL>TOPIC_CD</COL>
        <COL>TOPIC_NAME</COL>
    </METADATA>
    <ROWS>
        <ROW>
            <P_ID/>
            <PROJECT_NAME/>
            <LICENSE_ID/>
            <LICENSE_NAME/>
            <LICENSE_DISPLAY/>
            <SIZE>14</SIZE>
            <TOPIC_CD/>
            <TOPIC_NAME/>
        </ROW>
        <ROW>
            <P_ID>121093</P_ID>
            <PROJECT_NAME/>
            <LICENSE_ID>1002</LICENSE_ID>
            <LICENSE_NAME/>
            <LICENSE_DISPLAY/>
            <SIZE>2</SIZE>
            <TOPIC_CD>020123</TOPIC_CD>
            <TOPIC_NAME/>
        </ROW>
        <ROW>
            <P_ID>360358</P_ID>
            <PROJECT_NAME/>
            <LICENSE_ID/>
            <LICENSE_NAME/>
            <LICENSE_DISPLAY/>
            <SIZE>1</SIZE>
            <TOPIC_CD/>
            <TOPIC_NAME/>
        </ROW>
        <ROW>
            <P_ID>254256</P_ID>
            <PROJECT_NAME/>
            <LICENSE_ID>1005,1005</LICENSE_ID>
            <LICENSE_NAME/>
            <LICENSE_DISPLAY/>
            <SIZE>1</SIZE>
            <TOPIC_CD>020076</TOPIC_CD>
            <TOPIC_NAME/>
        </ROW>
        <ROW>
            <P_ID>170475</P_ID>
            <PROJECT_NAME/>
            <LICENSE_ID>1010</LICENSE_ID>
            <LICENSE_NAME/>
            <LICENSE_DISPLAY/>
            <SIZE>1</SIZE>
            <TOPIC_CD>020036|020090|020091|020095</TOPIC_CD>
            <TOPIC_NAME/>
        </ROW>
        <ROW>
            <P_ID>102041</P_ID>
            <PROJECT_NAME/>
            <LICENSE_ID>1004</LICENSE_ID>
            <LICENSE_NAME/>
            <LICENSE_DISPLAY/>
            <SIZE>1</SIZE>
            <TOPIC_CD>020020|020144</TOPIC_CD>
            <TOPIC_NAME/>
        </ROW>
        <ROW>
            <P_ID>121939</P_ID>
            <PROJECT_NAME/>
            <LICENSE_ID>1004</LICENSE_ID>
            <LICENSE_NAME/>
            <LICENSE_DISPLAY/>
            <SIZE>6</SIZE>
            <TOPIC_CD>020059|020091|020097</TOPIC_CD>
            <TOPIC_NAME/>
        </ROW>
        <ROW>
            <P_ID>360428</P_ID>
            <PROJECT_NAME/>
            <LICENSE_ID/>
            <LICENSE_NAME/>
            <LICENSE_DISPLAY/>
            <SIZE>1</SIZE>
            <TOPIC_CD/>
            <TOPIC_NAME/>
        </ROW>
        <ROW>
            <P_ID>16473</P_ID>
            <PROJECT_NAME/>
            <LICENSE_ID>1002</LICENSE_ID>
            <LICENSE_NAME/>
            <LICENSE_DISPLAY/>
            <SIZE>1</SIZE>
            <TOPIC_CD>020153|020154|020156</TOPIC_CD>
            <TOPIC_NAME/>
        </ROW>
        <ROW>
            <P_ID>338074</P_ID>
            <PROJECT_NAME/>
            <LICENSE_ID>1004</LICENSE_ID>
            <LICENSE_NAME/>
            <LICENSE_DISPLAY/>
            <SIZE>1</SIZE>
            <TOPIC_CD>020086|020111</TOPIC_CD>
            <TOPIC_NAME/>
        </ROW>
        <ROW>
            <P_ID>208041</P_ID>
            <PROJECT_NAME/>
            <LICENSE_ID>1004,1004</LICENSE_ID>
            <LICENSE_NAME/>
            <LICENSE_DISPLAY/>
            <SIZE>4</SIZE>
            <TOPIC_CD>020080|020101|020122</TOPIC_CD>
            <TOPIC_NAME/>
        </ROW>
        <ROW>
            <P_ID>228387</P_ID>
            <PROJECT_NAME/>
            <LICENSE_ID>1002</LICENSE_ID>
            <LICENSE_NAME/>
            <LICENSE_DISPLAY/>
            <SIZE>3</SIZE>
            <TOPIC_CD>020153</TOPIC_CD>
            <TOPIC_NAME/>
        </ROW>
        <ROW>
            <P_ID>284499</P_ID>
            <PROJECT_NAME/>
            <LICENSE_ID>1004,1005,1004,1005</LICENSE_ID>
            <LICENSE_NAME/>
            <LICENSE_DISPLAY/>
            <SIZE>10</SIZE>
            <TOPIC_CD>020097|020098|020153</TOPIC_CD>
            <TOPIC_NAME/>
        </ROW>
        <ROW>
            <P_ID>238992</P_ID>
            <PROJECT_NAME/>
            <LICENSE_ID>1005</LICENSE_ID>
            <LICENSE_NAME/>
            <LICENSE_DISPLAY/>
            <SIZE>5</SIZE>
            <TOPIC_CD/>
            <TOPIC_NAME/>
        </ROW>
        <ROW>
            <P_ID>150898</P_ID>
            <PROJECT_NAME/>
            <LICENSE_ID>1004,1083</LICENSE_ID>
            <LICENSE_NAME/>
            <LICENSE_DISPLAY/>
            <SIZE>6</SIZE>
            <TOPIC_CD>020054|020055</TOPIC_CD>
            <TOPIC_NAME/>
        </ROW>
        <ROW>
            <P_ID>251283</P_ID>
            <PROJECT_NAME/>
            <LICENSE_ID>1072</LICENSE_ID>
            <LICENSE_NAME/>
            <LICENSE_DISPLAY/>
            <SIZE>1</SIZE>
            <TOPIC_CD>020158</TOPIC_CD>
            <TOPIC_NAME/>
        </ROW>
        <ROW>
            <P_ID>57080</P_ID>
            <PROJECT_NAME/>
            <LICENSE_ID>1072</LICENSE_ID>
            <LICENSE_NAME/>
            <LICENSE_DISPLAY/>
            <SIZE>2</SIZE>
            <TOPIC_CD/>
            <TOPIC_NAME/>
        </ROW>
        <ROW>
            <P_ID>169161</P_ID>
            <PROJECT_NAME/>
            <LICENSE_ID>1004,1005</LICENSE_ID>
            <LICENSE_NAME/>
            <LICENSE_DISPLAY/>
            <SIZE>13</SIZE>
            <TOPIC_CD>020083|020153</TOPIC_CD>
            <TOPIC_NAME/>
        </ROW>
        <ROW>
            <P_ID>169162</P_ID>
            <PROJECT_NAME/>
            <LICENSE_ID/>
            <LICENSE_NAME/>
            <LICENSE_DISPLAY/>
            <SIZE>1</SIZE>
            <TOPIC_CD/>
            <TOPIC_NAME/>
        </ROW>
        <ROW>
            <P_ID>332056</P_ID>
            <PROJECT_NAME/>
            <LICENSE_ID>1003,1092,1093</LICENSE_ID>
            <LICENSE_NAME/>
            <LICENSE_DISPLAY/>
            <SIZE>8</SIZE>
            <TOPIC_CD>020058|020086|020137</TOPIC_CD>
            <TOPIC_NAME/>
        </ROW>
        <ROW>
            <P_ID>54845</P_ID>
            <PROJECT_NAME/>
            <LICENSE_ID/>
            <LICENSE_NAME/>
            <LICENSE_DISPLAY/>
            <SIZE>1</SIZE>
            <TOPIC_CD/>
            <TOPIC_NAME/>
        </ROW>
        <ROW>
            <P_ID>118836</P_ID>
            <PROJECT_NAME/>
            <LICENSE_ID/>
            <LICENSE_NAME/>
            <LICENSE_DISPLAY/>
            <SIZE>4</SIZE>
            <TOPIC_CD/>
            <TOPIC_NAME/>
        </ROW>
        <ROW>
            <P_ID>153259</P_ID>
            <PROJECT_NAME/>
            <LICENSE_ID/>
            <LICENSE_NAME/>
            <LICENSE_DISPLAY/>
            <SIZE>11</SIZE>
            <TOPIC_CD/>
            <TOPIC_NAME/>
        </ROW>
        <ROW>
            <P_ID>185307</P_ID>
            <PROJECT_NAME/>
            <LICENSE_ID>1017</LICENSE_ID>
            <LICENSE_NAME/>
            <LICENSE_DISPLAY/>
            <SIZE>11</SIZE>
            <TOPIC_CD>020083</TOPIC_CD>
            <TOPIC_NAME/>
        </ROW>
        <ROW>
            <P_ID>231745</P_ID>
            <PROJECT_NAME/>
            <LICENSE_ID>1005</LICENSE_ID>
            <LICENSE_NAME/>
            <LICENSE_DISPLAY/>
            <SIZE>21</SIZE>
            <TOPIC_CD>020020|020147|020148</TOPIC_CD>
            <TOPIC_NAME/>
        </ROW>
        <ROW>
            <P_ID>222436</P_ID>
            <PROJECT_NAME/>
            <LICENSE_ID>1003,1092,1093</LICENSE_ID>
            <LICENSE_NAME/>
            <LICENSE_DISPLAY/>
            <SIZE>3</SIZE>
            <TOPIC_CD>020001|020083|020097</TOPIC_CD>
            <TOPIC_NAME/>
        </ROW>
        <ROW>
            <P_ID>332913</P_ID>
            <PROJECT_NAME/>
            <LICENSE_ID>1018,1078</LICENSE_ID>
            <LICENSE_NAME/>
            <LICENSE_DISPLAY/>
            <SIZE>2</SIZE>
            <TOPIC_CD>020054|020153|020156</TOPIC_CD>
            <TOPIC_NAME/>
        </ROW>
        <ROW>
            <P_ID>45556</P_ID>
            <PROJECT_NAME/>
            <LICENSE_ID>1004</LICENSE_ID>
            <LICENSE_NAME/>
            <LICENSE_DISPLAY/>
            <SIZE>11</SIZE>
            <TOPIC_CD>020054</TOPIC_CD>
            <TOPIC_NAME/>
        </ROW>
        <ROW>
            <P_ID>368441</P_ID>
            <PROJECT_NAME/>
            <LICENSE_ID>1005</LICENSE_ID>
            <LICENSE_NAME/>
            <LICENSE_DISPLAY/>
            <SIZE>2</SIZE>
            <TOPIC_CD>020128</TOPIC_CD>
            <TOPIC_NAME/>
        </ROW>
        <ROW>
            <P_ID>27804</P_ID>
            <PROJECT_NAME/>
            <LICENSE_ID>1002</LICENSE_ID>
            <LICENSE_NAME/>
            <LICENSE_DISPLAY/>
            <SIZE>1</SIZE>
            <TOPIC_CD>020156</TOPIC_CD>
            <TOPIC_NAME/>
        </ROW>
        <ROW>
            <P_ID>149595</P_ID>
            <PROJECT_NAME/>
            <LICENSE_ID>1004,1083,1004,1083</LICENSE_ID>
            <LICENSE_NAME/>
            <LICENSE_DISPLAY/>
            <SIZE>9</SIZE>
            <TOPIC_CD>020015|020089|020091</TOPIC_CD>
            <TOPIC_NAME/>
        </ROW>
        <ROW>
            <P_ID>39361</P_ID>
            <PROJECT_NAME/>
            <LICENSE_ID>1004</LICENSE_ID>
            <LICENSE_NAME/>
            <LICENSE_DISPLAY/>
            <SIZE>5</SIZE>
            <TOPIC_CD>020054|020074|020144</TOPIC_CD>
            <TOPIC_NAME/>
        </ROW>
        <ROW>
            <P_ID>332217</P_ID>
            <PROJECT_NAME/>
            <LICENSE_ID/>
            <LICENSE_NAME/>
            <LICENSE_DISPLAY/>
            <SIZE>4</SIZE>
            <TOPIC_CD/>
            <TOPIC_NAME/>
        </ROW>
        <ROW>
            <P_ID>93743</P_ID>
            <PROJECT_NAME/>
            <LICENSE_ID/>
            <LICENSE_NAME/>
            <LICENSE_DISPLAY/>
            <SIZE>2</SIZE>
            <TOPIC_CD/>
            <TOPIC_NAME/>
        </ROW>
        <ROW>
            <P_ID>53676</P_ID>
            <PROJECT_NAME/>
            <LICENSE_ID>1004</LICENSE_ID>
            <LICENSE_NAME/>
            <LICENSE_DISPLAY/>
            <SIZE>2</SIZE>
            <TOPIC_CD>020095|020101|020104</TOPIC_CD>
            <TOPIC_NAME/>
        </ROW>
        <ROW>
            <P_ID>257559</P_ID>
            <PROJECT_NAME/>
            <LICENSE_ID>1004,1004</LICENSE_ID>
            <LICENSE_NAME/>
            <LICENSE_DISPLAY/>
            <SIZE>2</SIZE>
            <TOPIC_CD>020057|020060|020097</TOPIC_CD>
            <TOPIC_NAME/>
        </ROW>
        <ROW>
            <P_ID>232355</P_ID>
            <PROJECT_NAME/>
            <LICENSE_ID>1004</LICENSE_ID>
            <LICENSE_NAME/>
            <LICENSE_DISPLAY/>
            <SIZE>13</SIZE>
            <TOPIC_CD>020057|020058|020059</TOPIC_CD>
            <TOPIC_NAME/>
        </ROW>
        <ROW>
            <P_ID>337104</P_ID>
            <PROJECT_NAME/>
            <LICENSE_ID>1004,1083</LICENSE_ID>
            <LICENSE_NAME/>
            <LICENSE_DISPLAY/>
            <SIZE>2</SIZE>
            <TOPIC_CD>020057|020073|020101</TOPIC_CD>
            <TOPIC_NAME/>
        </ROW>
        <ROW>
            <P_ID>178713</P_ID>
            <PROJECT_NAME/>
            <LICENSE_ID>1004</LICENSE_ID>
            <LICENSE_NAME/>
            <LICENSE_DISPLAY/>
            <SIZE>2</SIZE>
            <TOPIC_CD>020090|020095</TOPIC_CD>
            <TOPIC_NAME/>
        </ROW>
        <ROW>
            <P_ID>55488</P_ID>
            <PROJECT_NAME/>
            <LICENSE_ID/>
            <LICENSE_NAME/>
            <LICENSE_DISPLAY/>
            <SIZE>1</SIZE>
            <TOPIC_CD/>
            <TOPIC_NAME/>
        </ROW>
        <ROW>
            <P_ID>186741</P_ID>
            <PROJECT_NAME/>
            <LICENSE_ID>1005</LICENSE_ID>
            <LICENSE_NAME/>
            <LICENSE_DISPLAY/>
            <SIZE>2</SIZE>
            <TOPIC_CD>020052|020061|020086</TOPIC_CD>
            <TOPIC_NAME/>
        </ROW>
        <ROW>
            <P_ID>186738</P_ID>
            <PROJECT_NAME/>
            <LICENSE_ID>1004,1005,1007</LICENSE_ID>
            <LICENSE_NAME/>
            <LICENSE_DISPLAY/>
            <SIZE>8</SIZE>
            <TOPIC_CD>020054</TOPIC_CD>
            <TOPIC_NAME/>
        </ROW>
        <ROW>
            <P_ID>341627</P_ID>
            <PROJECT_NAME/>
            <LICENSE_ID>1005</LICENSE_ID>
            <LICENSE_NAME/>
            <LICENSE_DISPLAY/>
            <SIZE>3</SIZE>
            <TOPIC_CD>020089|020091</TOPIC_CD>
            <TOPIC_NAME/>
        </ROW>
        <ROW>
            <P_ID>219431</P_ID>
            <PROJECT_NAME/>
            <LICENSE_ID/>
            <LICENSE_NAME/>
            <LICENSE_DISPLAY/>
            <SIZE>5</SIZE>
            <TOPIC_CD/>
            <TOPIC_NAME/>
        </ROW>
        <ROW>
            <P_ID>396271</P_ID>
            <PROJECT_NAME/>
            <LICENSE_ID/>
            <LICENSE_NAME/>
            <LICENSE_DISPLAY/>
            <SIZE>2</SIZE>
            <TOPIC_CD/>
            <TOPIC_NAME/>
        </ROW>
        <ROW>
            <P_ID>186033</P_ID>
            <PROJECT_NAME/>
            <LICENSE_ID>1004</LICENSE_ID>
            <LICENSE_NAME/>
            <LICENSE_DISPLAY/>
            <SIZE>5</SIZE>
            <TOPIC_CD/>
            <TOPIC_NAME/>
        </ROW>
        <ROW>
            <P_ID>98720</P_ID>
            <PROJECT_NAME/>
            <LICENSE_ID>1002</LICENSE_ID>
            <LICENSE_NAME/>
            <LICENSE_DISPLAY/>
            <SIZE>2</SIZE>
            <TOPIC_CD>020086</TOPIC_CD>
            <TOPIC_NAME/>
        </ROW>
        <ROW>
            <P_ID>333580</P_ID>
            <PROJECT_NAME/>
            <LICENSE_ID/>
            <LICENSE_NAME/>
            <LICENSE_DISPLAY/>
            <SIZE>3</SIZE>
            <TOPIC_CD/>
            <TOPIC_NAME/>
        </ROW>
        <ROW>
            <P_ID>223889</P_ID>
            <PROJECT_NAME/>
            <LICENSE_ID/>
            <LICENSE_NAME/>
            <LICENSE_DISPLAY/>
            <SIZE>7</SIZE>
            <TOPIC_CD/>
            <TOPIC_NAME/>
        </ROW>
        <ROW>
            <P_ID>248422</P_ID>
            <PROJECT_NAME/>
            <LICENSE_ID>1005</LICENSE_ID>
            <LICENSE_NAME/>
            <LICENSE_DISPLAY/>
            <SIZE>1</SIZE>
            <TOPIC_CD>020019|020073|020096</TOPIC_CD>
            <TOPIC_NAME/>
        </ROW>
        <ROW>
            <P_ID>115264</P_ID>
            <PROJECT_NAME/>
            <LICENSE_ID>1005</LICENSE_ID>
            <LICENSE_NAME/>
            <LICENSE_DISPLAY/>
            <SIZE>1</SIZE>
            <TOPIC_CD>020061|020111</TOPIC_CD>
            <TOPIC_NAME/>
        </ROW>
        <ROW>
            <P_ID>261501</P_ID>
            <PROJECT_NAME/>
            <LICENSE_ID>1004</LICENSE_ID>
            <LICENSE_NAME/>
            <LICENSE_DISPLAY/>
            <SIZE>6</SIZE>
            <TOPIC_CD>020036|020117|020155</TOPIC_CD>
            <TOPIC_NAME/>
        </ROW>
        <ROW>
            <P_ID>117055</P_ID>
            <PROJECT_NAME/>
            <LICENSE_ID>1005,1005</LICENSE_ID>
            <LICENSE_NAME/>
            <LICENSE_DISPLAY/>
            <SIZE>1</SIZE>
            <TOPIC_CD>020083|020102|020123|020129</TOPIC_CD>
            <TOPIC_NAME/>
        </ROW>
        <ROW>
            <P_ID>175005</P_ID>
            <PROJECT_NAME/>
            <LICENSE_ID>1004</LICENSE_ID>
            <LICENSE_NAME/>
            <LICENSE_DISPLAY/>
            <SIZE>2</SIZE>
            <TOPIC_CD/>
            <TOPIC_NAME/>
        </ROW>
        <ROW>
            <P_ID>52575</P_ID>
            <PROJECT_NAME/>
            <LICENSE_ID>1002</LICENSE_ID>
            <LICENSE_NAME/>
            <LICENSE_DISPLAY/>
            <SIZE>3</SIZE>
            <TOPIC_CD>020096|020111|020144</TOPIC_CD>
            <TOPIC_NAME/>
        </ROW>
        <ROW>
            <P_ID>387794</P_ID>
            <PROJECT_NAME/>
            <LICENSE_ID>1005</LICENSE_ID>
            <LICENSE_NAME/>
            <LICENSE_DISPLAY/>
            <SIZE>6</SIZE>
            <TOPIC_CD>020049|020050</TOPIC_CD>
            <TOPIC_NAME/>
        </ROW>
        <ROW>
            <P_ID>392900</P_ID>
            <PROJECT_NAME/>
            <LICENSE_ID/>
            <LICENSE_NAME/>
            <LICENSE_DISPLAY/>
            <SIZE>2</SIZE>
            <TOPIC_CD/>
            <TOPIC_NAME/>
        </ROW>
        <ROW>
            <P_ID>209722</P_ID>
            <PROJECT_NAME/>
            <LICENSE_ID>1003,1092,1093</LICENSE_ID>
            <LICENSE_NAME/>
            <LICENSE_DISPLAY/>
            <SIZE>3</SIZE>
            <TOPIC_CD>020080</TOPIC_CD>
            <TOPIC_NAME/>
        </ROW>
        <ROW>
            <P_ID>364430</P_ID>
            <PROJECT_NAME/>
            <LICENSE_ID>1073,1083</LICENSE_ID>
            <LICENSE_NAME/>
            <LICENSE_DISPLAY/>
            <SIZE>1</SIZE>
            <TOPIC_CD>020068|020069|020071|020080</TOPIC_CD>
            <TOPIC_NAME/>
        </ROW>
        <ROW>
            <P_ID>121640</P_ID>
            <PROJECT_NAME/>
            <LICENSE_ID>1002,1004</LICENSE_ID>
            <LICENSE_NAME/>
            <LICENSE_DISPLAY/>
            <SIZE>1</SIZE>
            <TOPIC_CD>020013|020091</TOPIC_CD>
            <TOPIC_NAME/>
        </ROW>
        <ROW>
            <P_ID>154925</P_ID>
            <PROJECT_NAME/>
            <LICENSE_ID>1004</LICENSE_ID>
            <LICENSE_NAME/>
            <LICENSE_DISPLAY/>
            <SIZE>10</SIZE>
            <TOPIC_CD>020064|020090</TOPIC_CD>
            <TOPIC_NAME/>
        </ROW>
        <ROW>
            <P_ID>367459</P_ID>
            <PROJECT_NAME/>
            <LICENSE_ID>1004,1007</LICENSE_ID>
            <LICENSE_NAME/>
            <LICENSE_DISPLAY/>
            <SIZE>3</SIZE>
            <TOPIC_CD>020069|020080|020137</TOPIC_CD>
            <TOPIC_NAME/>
        </ROW>
        <ROW>
            <P_ID>230842</P_ID>
            <PROJECT_NAME/>
            <LICENSE_ID>1005,1005</LICENSE_ID>
            <LICENSE_NAME/>
            <LICENSE_DISPLAY/>
            <SIZE>4</SIZE>
            <TOPIC_CD>020117|020121|020129</TOPIC_CD>
            <TOPIC_NAME/>
        </ROW>
        <ROW>
            <P_ID>339778</P_ID>
            <PROJECT_NAME/>
            <LICENSE_ID>1002</LICENSE_ID>
            <LICENSE_NAME/>
            <LICENSE_DISPLAY/>
            <SIZE>1</SIZE>
            <TOPIC_CD>020091|020097</TOPIC_CD>
            <TOPIC_NAME/>
        </ROW>
        <ROW>
            <P_ID>279188</P_ID>
            <PROJECT_NAME/>
            <LICENSE_ID/>
            <LICENSE_NAME/>
            <LICENSE_DISPLAY/>
            <SIZE>1</SIZE>
            <TOPIC_CD/>
            <TOPIC_NAME/>
        </ROW>
        <ROW>
            <P_ID>62490</P_ID>
            <PROJECT_NAME/>
            <LICENSE_ID>1003,1092,1093</LICENSE_ID>
            <LICENSE_NAME/>
            <LICENSE_DISPLAY/>
            <SIZE>1</SIZE>
            <TOPIC_CD>020001|020054|020102|020103|020117|020123</TOPIC_CD>
            <TOPIC_NAME/>
        </ROW>
        <ROW>
            <P_ID>205447</P_ID>
            <PROJECT_NAME/>
            <LICENSE_ID>1004</LICENSE_ID>
            <LICENSE_NAME/>
            <LICENSE_DISPLAY/>
            <SIZE>3</SIZE>
            <TOPIC_CD/>
            <TOPIC_NAME/>
        </ROW>
        <ROW>
            <P_ID>114887</P_ID>
            <PROJECT_NAME/>
            <LICENSE_ID>1005</LICENSE_ID>
            <LICENSE_NAME/>
            <LICENSE_DISPLAY/>
            <SIZE>4</SIZE>
            <TOPIC_CD>020102|020124|020153</TOPIC_CD>
            <TOPIC_NAME/>
        </ROW>
        <ROW>
            <P_ID>285553</P_ID>
            <PROJECT_NAME/>
            <LICENSE_ID/>
            <LICENSE_NAME/>
            <LICENSE_DISPLAY/>
            <SIZE>1</SIZE>
            <TOPIC_CD/>
            <TOPIC_NAME/>
        </ROW>
        <ROW>
            <P_ID>249056</P_ID>
            <PROJECT_NAME/>
            <LICENSE_ID>1002,1002</LICENSE_ID>
            <LICENSE_NAME/>
            <LICENSE_DISPLAY/>
            <SIZE>8</SIZE>
            <TOPIC_CD>020054|020096|020153|020155</TOPIC_CD>
            <TOPIC_NAME/>
        </ROW>
        <ROW>
            <P_ID>10950</P_ID>
            <PROJECT_NAME/>
            <LICENSE_ID>1004</LICENSE_ID>
            <LICENSE_NAME/>
            <LICENSE_DISPLAY/>
            <SIZE>9</SIZE>
            <TOPIC_CD>020052|020109|020153|020155|020156</TOPIC_CD>
            <TOPIC_NAME/>
        </ROW>
        <ROW>
            <P_ID>37943</P_ID>
            <PROJECT_NAME/>
            <LICENSE_ID>1007</LICENSE_ID>
            <LICENSE_NAME/>
            <LICENSE_DISPLAY/>
            <SIZE>3</SIZE>
            <TOPIC_CD/>
            <TOPIC_NAME/>
        </ROW>
        <ROW>
            <P_ID>127057</P_ID>
            <PROJECT_NAME/>
            <LICENSE_ID>1005</LICENSE_ID>
            <LICENSE_NAME/>
            <LICENSE_DISPLAY/>
            <SIZE>4</SIZE>
            <TOPIC_CD>020068|020071|020080</TOPIC_CD>
            <TOPIC_NAME/>
        </ROW>
        <ROW>
            <P_ID>189320</P_ID>
            <PROJECT_NAME/>
            <LICENSE_ID>1002,1002</LICENSE_ID>
            <LICENSE_NAME/>
            <LICENSE_DISPLAY/>
            <SIZE>19</SIZE>
            <TOPIC_CD>020091|020101|020117|020123</TOPIC_CD>
            <TOPIC_NAME/>
        </ROW>
        <ROW>
            <P_ID>176441</P_ID>
            <PROJECT_NAME/>
            <LICENSE_ID/>
            <LICENSE_NAME/>
            <LICENSE_DISPLAY/>
            <SIZE>3</SIZE>
            <TOPIC_CD/>
            <TOPIC_NAME/>
        </ROW>
        <ROW>
            <P_ID>106207</P_ID>
            <PROJECT_NAME/>
            <LICENSE_ID>1005</LICENSE_ID>
            <LICENSE_NAME/>
            <LICENSE_DISPLAY/>
            <SIZE>2</SIZE>
            <TOPIC_CD>020013|020097|020103</TOPIC_CD>
            <TOPIC_NAME/>
        </ROW>
        <ROW>
            <P_ID>5552</P_ID>
            <PROJECT_NAME/>
            <LICENSE_ID/>
            <LICENSE_NAME/>
            <LICENSE_DISPLAY/>
            <SIZE>3</SIZE>
            <TOPIC_CD/>
            <TOPIC_NAME/>
        </ROW>
        <ROW>
            <P_ID>63915</P_ID>
            <PROJECT_NAME/>
            <LICENSE_ID>1069</LICENSE_ID>
            <LICENSE_NAME/>
            <LICENSE_DISPLAY/>
            <SIZE>12</SIZE>
            <TOPIC_CD/>
            <TOPIC_NAME/>
        </ROW>
        <ROW>
            <P_ID>276274</P_ID>
            <PROJECT_NAME/>
            <LICENSE_ID>1005</LICENSE_ID>
            <LICENSE_NAME/>
            <LICENSE_DISPLAY/>
            <SIZE>2</SIZE>
            <TOPIC_CD/>
            <TOPIC_NAME/>
        </ROW>
        <ROW>
            <P_ID>38472</P_ID>
            <PROJECT_NAME/>
            <LICENSE_ID>1005</LICENSE_ID>
            <LICENSE_NAME/>
            <LICENSE_DISPLAY/>
            <SIZE>3</SIZE>
            <TOPIC_CD>020019|020071|020096</TOPIC_CD>
            <TOPIC_NAME/>
        </ROW>
        <ROW>
            <P_ID>20829</P_ID>
            <PROJECT_NAME/>
            <LICENSE_ID/>
            <LICENSE_NAME/>
            <LICENSE_DISPLAY/>
            <SIZE>4</SIZE>
            <TOPIC_CD/>
            <TOPIC_NAME/>
        </ROW>
        <ROW>
            <P_ID>81754</P_ID>
            <PROJECT_NAME/>
            <LICENSE_ID/>
            <LICENSE_NAME/>
            <LICENSE_DISPLAY/>
            <SIZE>7</SIZE>
            <TOPIC_CD/>
            <TOPIC_NAME/>
        </ROW>
        <ROW>
            <P_ID>350450</P_ID>
            <PROJECT_NAME/>
            <LICENSE_ID>1005</LICENSE_ID>
            <LICENSE_NAME/>
            <LICENSE_DISPLAY/>
            <SIZE>1</SIZE>
            <TOPIC_CD>020097</TOPIC_CD>
            <TOPIC_NAME/>
        </ROW>
        <ROW>
            <P_ID>263397</P_ID>
            <PROJECT_NAME/>
            <LICENSE_ID/>
            <LICENSE_NAME/>
            <LICENSE_DISPLAY/>
            <SIZE>1</SIZE>
            <TOPIC_CD/>
            <TOPIC_NAME/>
        </ROW>
        <ROW>
            <P_ID>42980</P_ID>
            <PROJECT_NAME/>
            <LICENSE_ID>1005,1083</LICENSE_ID>
            <LICENSE_NAME/>
            <LICENSE_DISPLAY/>
            <SIZE>17</SIZE>
            <TOPIC_CD>020013|020054|020137</TOPIC_CD>
            <TOPIC_NAME/>
        </ROW>
        <ROW>
            <P_ID>312955</P_ID>
            <PROJECT_NAME/>
            <LICENSE_ID>1005</LICENSE_ID>
            <LICENSE_NAME/>
            <LICENSE_DISPLAY/>
            <SIZE>2</SIZE>
            <TOPIC_CD>020014|020099|020144</TOPIC_CD>
            <TOPIC_NAME/>
        </ROW>
        <ROW>
            <P_ID>280114</P_ID>
            <PROJECT_NAME/>
            <LICENSE_ID>1005</LICENSE_ID>
            <LICENSE_NAME/>
            <LICENSE_DISPLAY/>
            <SIZE>5</SIZE>
            <TOPIC_CD>020015|020153</TOPIC_CD>
            <TOPIC_NAME/>
        </ROW>
        <ROW>
            <P_ID>52121</P_ID>
            <PROJECT_NAME/>
            <LICENSE_ID>1004,1010</LICENSE_ID>
            <LICENSE_NAME/>
            <LICENSE_DISPLAY/>
            <SIZE>4</SIZE>
            <TOPIC_CD>020096</TOPIC_CD>
            <TOPIC_NAME/>
        </ROW>
        <ROW>
            <P_ID>29981</P_ID>
            <PROJECT_NAME/>
            <LICENSE_ID/>
            <LICENSE_NAME/>
            <LICENSE_DISPLAY/>
            <SIZE>1</SIZE>
            <TOPIC_CD/>
            <TOPIC_NAME/>
        </ROW>
        <ROW>
            <P_ID>56433</P_ID>
            <PROJECT_NAME/>
            <LICENSE_ID>1002</LICENSE_ID>
            <LICENSE_NAME/>
            <LICENSE_DISPLAY/>
            <SIZE>1</SIZE>
            <TOPIC_CD>020091|020097|020101</TOPIC_CD>
            <TOPIC_NAME/>
        </ROW>
        <ROW>
            <P_ID>51575</P_ID>
            <PROJECT_NAME/>
            <LICENSE_ID>1010</LICENSE_ID>
            <LICENSE_NAME/>
            <LICENSE_DISPLAY/>
            <SIZE>4</SIZE>
            <TOPIC_CD>020035|020091|020102|020111|020117</TOPIC_CD>
            <TOPIC_NAME/>
        </ROW>
        <ROW>
            <P_ID>416434</P_ID>
            <PROJECT_NAME/>
            <LICENSE_ID>1002</LICENSE_ID>
            <LICENSE_NAME/>
            <LICENSE_DISPLAY/>
            <SIZE>2</SIZE>
            <TOPIC_CD>020091</TOPIC_CD>
            <TOPIC_NAME/>
        </ROW>
        <ROW>
            <P_ID>313492</P_ID>
            <PROJECT_NAME/>
            <LICENSE_ID>1002</LICENSE_ID>
            <LICENSE_NAME/>
            <LICENSE_DISPLAY/>
            <SIZE>2</SIZE>
            <TOPIC_CD/>
            <TOPIC_NAME/>
        </ROW>
        <ROW>
            <P_ID>100223</P_ID>
            <PROJECT_NAME/>
            <LICENSE_ID/>
            <LICENSE_NAME/>
            <LICENSE_DISPLAY/>
            <SIZE>1</SIZE>
            <TOPIC_CD/>
            <TOPIC_NAME/>
        </ROW>
        <ROW>
            <P_ID>280873</P_ID>
            <PROJECT_NAME/>
            <LICENSE_ID>1005</LICENSE_ID>
            <LICENSE_NAME/>
            <LICENSE_DISPLAY/>
            <SIZE>11</SIZE>
            <TOPIC_CD>020054|020058|020137</TOPIC_CD>
            <TOPIC_NAME/>
        </ROW>
        <ROW>
            <P_ID>255473</P_ID>
            <PROJECT_NAME/>
            <LICENSE_ID>1083</LICENSE_ID>
            <LICENSE_NAME/>
            <LICENSE_DISPLAY/>
            <SIZE>1</SIZE>
            <TOPIC_CD/>
            <TOPIC_NAME/>
        </ROW>
        <ROW>
            <P_ID>94692</P_ID>
            <PROJECT_NAME/>
            <LICENSE_ID/>
            <LICENSE_NAME/>
            <LICENSE_DISPLAY/>
            <SIZE>2</SIZE>
            <TOPIC_CD/>
            <TOPIC_NAME/>
        </ROW>
    </ROWS>
</TABLE>
